Workbook

Sheet Overview
A1: Company | B1: Price | C1: Market Cap | D1: Market Cap (in Bil) | E1: Net Debt (in Bil) | F1: EV (in Bil) | G1: Revenue (in Bil) | H1: EBITDA (in Bil) | I1: Net Income (in Bil) | J1: EPS (diluted) | K1: Book Value (total equity) | L1: Book Value per share (in Bil) | M1: Free Cash Flow (in Bil)
A2: #VALUE! | B2: {=_FV(A2,"Prezzo")} -> 206.8568 | C2: {=_FV(A2,"Capitalizzazione di mercato",TRUE)} -> 2176459000000 | D2: =C2/1000000000 -> 2176.459 | E2: =(AMZN!G22-AMZN!G24) -> 67.04 | F2: =D2+E2 -> 2243.499 | G2: =AMZN!G2 -> 650.31 | H2: =AMZN!G10 -> 130.24 | I2: =AMZN!G12 -> 65.94 | J2: =AMZN!G15 -> 6.14 | K2: =AMZN!G23 -> 305.87 | L2: =AMZN!G27 -> 28.82 | M2: =AMZN!G35 -> 42.22
A3: #VALUE! | B3: {=_FV(A3,"Prezzo")} -> 7.748 | C3: {=_FV(A3,"Capitalizzazione di mercato",TRUE)} -> 11105730000 | D3: =C3/1000000000 -> 11.10573 | E3: =BPER!G14-BPER!G16 -> 111.56 | F3: =D3+E3 -> 122.66573 | G3: =BPER!G2 -> 5.86 | I3: =BPER!G4 -> 1.39 | J3: =BPER!G7 -> 1.92 | K3: =BPER!G15 -> 11.99 | L3: =BPER!G18 -> 16.64 | M3: =BPER!G25 -> 2.66
A4: #VALUE! | B4: 44 | C4: {=_FV(A4,"Capitalizzazione di mercato",TRUE)} -> 8710555000 | D4: =C4/1000000000 -> 8.710555 | E4: =BUZZI!G22-BUZZI!G24 -> -0.43 | F4: =D4+E4 -> 8.280555 | G4: =BUZZI!G2 -> 4.31 | H4: =BUZZI!G10 -> 1.32 | I4: =BUZZI!G12 -> 0.94 | J4: =BUZZI!G15 -> 5.1 | K4: =BUZZI!G23 -> 5.63 | L4: =BUZZI!G27 -> 30.39 | M4: =BUZZI!G35 -> 0.55
A5: #VALUE! | B5: {=_FV(A5,"Prezzo")} -> 137.593 | C5: {=_FV(A5,"Capitalizzazione di mercato",TRUE)} -> 3357269199999 | D5: =C5/1000000000 -> 3357.2692 | E5: =NVDA!G22-NVDA!G24 -> -4.94 | F5: =D5+E5 -> 3352.3292 | G5: =NVDA!G2 -> 148.52 | H5: =NVDA!G10 -> 89.03 | I5: =NVDA!G12 -> 76.77 | J5: =NVDA!G15 -> 3.1 | K5: =NVDA!G23 -> 83.84 | L5: =NVDA!G27 -> 3.44 | M5: =NVDA!G35 -> 73.63
B9: EBITDA Margin (%) | C9: EV/EBITDA | D9: P/E | E9: P/B | F9: FCF Yield (%) | G9: ROE | H9: ROIC | I9: Reinvestment rate (capex ratio)
A10: AMAZON | B10: =H2/G2 -> 0.20027372 | C10: =F2/H2 -> 17.225883 | D10: =B2/J2 -> 33.690033 | E10: =D2/K2 -> 7.1156341 | F10: =M2/D2 -> 0.019398482 | G10: =I2/K2 -> 0.21558178 | I10: =AMZN!G34/AMZN!G10 -> 0.71475737
A11: BPER | B11: =H3/G3 -> 0 | C11: 0 | D11: =B3/J3 -> 4.0354167 | E11: =D3/K3 -> 0.92624937 | F11: =M3/D3 -> 0.239516 | G11: =I3/K3 -> 0.11592994 | I11: 0
A12: BUZZI | B12: =H4/G4 -> 0.3062645 | C12: =F4/H4 -> 6.2731477 | D12: =B4/J4 -> 8.627451 | E12: =D4/K4 -> 1.5471679 | F12: =M4/D4 -> 0.063141786 | G12: =I4/K4 -> 0.1669627 | I12: =BUZZI!G34/BUZZI!G10 -> 0.34090909
A13: NVIDIA | B13: =H5/G5 -> 0.59944789 | C13: =F5/H5 -> 37.653928 | D13: =B5/J5 -> 44.384839 | E13: =D5/K5 -> 40.043764 | F13: =M5/D5 -> 0.021931515 | G13: =I5/K5 -> 0.91567271 | I13: =NVDA!G34/NVDA!G10 -> 0.045939571

Sheet AMZN
A1: Income Statement (in Bil, except ratios) | B1: 44166 | C1: 44531 | D1: 44896 | E1: 45261 | F1: 45627 | G1: 03/31/2025
A2: Revenue | B2: 386.06 | C2: 469.82 | D2: 513.98 | E2: 574.79 | F2: 637.96 | G2: 650.31
A3: Revenue Growth % | B3: 0.3762 | C3: 0.217 | D3: 0.094 | E3: 0.1183 | F3: 0.1099 | G3: 0.1008
A4: Gross Profit | B4: 152.76 | C4: 197.48 | D4: 225.15 | E4: 270.05 | F4: 311.67 | G4: 319.68
A5: Gross Profit Margin % | B5: 0.3957 | C5: 0.4203 | D5: 0.4381 | E5: 0.4698 | F5: 0.4885 | G5: 0.4916
A6: Operating Income | B6: 22.9 | C6: 24.88 | D6: 12.25 | E6: 36.85 | F6: 68.59 | G6: 71.69
A7: Operating Margin % | B7: 0.0593 | C7: 0.053 | D7: 0.0238 | E7: 0.0641 | F7: 0.1075 | G7: 0.1102
A8: EBIT | B8: 25.27 | C8: 39.51 | D8: -4.56 | E8: 37.79 | F8: 66.34 | G8: 74.86
A9: EBIT Margin % | B9: 0.0655 | C9: 0.0841 | D9: -0.0089 | E9: 0.0657 | F9: 0.104 | G9: 0.1151
A10: EBITDA | B10: 50.52 | C10: 73.81 | D10: 37.36 | E10: 86.45 | F10: 119.14 | G10: 130.24
A11: EBITDA Margin % | B11: 0.1309 | C11: 0.1571 | D11: 0.0727 | E11: 0.1504 | F11: 0.1867 | G11: 0.2003
A12: Net Income | B12: 21.33 | C12: 33.36 | D12: -2.72 | E12: 30.43 | F12: 59.25 | G12: 65.94
A13: Net Profit Margin % | B13: 0.0553 | C13: 0.071 | D13: -0.0053 | E13: 0.0529 | F13: 0.0929 | G13: 0.1014
... A16: Normalized EPS | B16: 2.09 | C16: 2.09 | D16: 0.95 | E16: 2.84 | F16: 5.71 | G16: 6.17
A17: Total Dividends per Share | B17: — | C17: — | D17: — | E17: — | F17: — | G17: —
A19: Balance Sheet (in Bil, except ratios) | B19: 44166 | C19: 44531 | D19: 44896 | E19: 45261 | F19: 45627 | G19: 03/31/2025
A20: Total Assets | B20: 321.2 | C20: 420.55 | D20: 462.68 | E20: 527.85 | F20: 624.89 | G20: 643.26
A21: Total Liabilities | B21: 227.79 | C21: 282.3 | D21: 316.63 | E21: 325.98 | F21: 338.92 | G21: 337.39
A22: Total Debt | B22: 84.39 | C22: 116.4 | D22: 140.12 | E22: 135.61 | F22: 130.9 | G22: 133.25
A23: Total Equity | B23: 93.4 | C23: 138.25 | D23: 146.04 | E23: 201.88 | F23: 285.97 | G23: 305.87
A24: Cash And Cash Equivalents | B24: 42.12 | C24: 36.22 | D24: 53.89 | E24: 73.39 | F24: 78.78 | G24: 66.21
A25: Working Capital | B25: 6.35 | C25: 19.31 | D25: -8.6 | E25: 7.43 | F25: 11.44 | G25: 8.47
A26: Shares Outstanding (Bil) | B26: 10.04 | C26: 10.14 | D26: 10.2 | E26: 10.33 | F26: 10.52 | G26: 10.52
A27: Book Value Per Share | B27: 9.28 | C27: 13.58 | D27: 14.26 | E27: 19.44 | F27: 27 | G27: 28.82
A28: Total Debt To Equity | B28: 0.9 | C28: 0.84 | D28: 0.96 | E28: 0.67 | F28: 0.46 | G28: 0.44
A30: Cash Flow Statement (in Bil, except ratios) | B30: 44166 | C30: 44531 | D30: 44896 | E30: 45261 | F30: 45627 | G30: 03/31/2025
A31: Cash From Operating Activities | B31: 66.06 | C31: 46.33 | D31: 46.75 | E31: 84.95 | F31: 115.88 | G31: 113.9
A32: Cash From Investing Activities | B32: -59.61 | C32: -58.15 | D32: -37.6 | E32: -49.83 | F32: -94.34 | G32: -106.28
A33: Cash From Financing Activities | B33: -1.1 | C33: 6.29 | D33: 9.72 | E33: -15.88 | F33: -11.81 | G33: -10.6
A34: Capital Expenditures | B34: 40.14 | C34: 61.05 | D34: 63.65 | E34: 52.73 | F34: 83 | G34: 93.09
A35: Free Cash Flow | B35: 12.44 | C35: 4.89 | D35: 3.99 | E35: 43.76 | F35: 48.42 | G35: 42.22
A36: Change in Cash | B36: 5.35 | C36: -5.54 | D36: 18.87 | E36: 19.23 | F36: 9.72 | G36: -2.98

Sheet BPER
A1: Income Statement (in Bil, except ratios) | B1: 44166 | C1: 44531 | D1: 44896 | E1: 45261 | F1: 45627 | G1: 03/31/2025
A2: Revenue | B2: 2.74 | C2: 3.68 | D2: 4.31 | E2: 5.9 | F2: 5.99 | G2: 5.86
A3: Revenue Growth % | B3: 0.0973 | C3: 0.3443 | D3: 0.163 | E3: 0.3675 | F3: 0.0193 | G3: 0.0147
A4: Net Income | B4: 0.25 | C4: 0.53 | D4: 1.45 | E4: 1.52 | F4: 1.4 | G4: 1.39
A5: Net Profit Margin % | B5: 0.0989 | C5: 0.1519 | D5: 0.3422 | E5: 0.263 | F5: 0.2402 | G5: 0.2431
A6: Basic EPS | B6: 0.72 | C6: 0.74 | D6: 2.05 | E6: 2.15 | F6: 1.98 | G6: 1.96
A7: Diluted EPS | B7: 0.68 | C7: 0.73 | D7: 2 | E7: 2.1 | F7: 1.94 | G7: 1.92
A8: Normalized EPS | B8: 1.32 | C8: 2.76 | D8: 0.66 | E8: 2.21 | F8: 2.2 | G8: 2.39
A9: Total Dividends per Share | B9: 0.73 | C9: 0.08 | D9: 0.12 | E9: 0.24 | F9: 0.6 | G9: 0.6
A11: Balance Sheet (in Bil, except ratios) | B11: 44166 | C11: 44531 | D11: 44896 | E11: 45261 | F11: 45627 | G11: 03/31/2025
A12: Total Assets | B12: 93.05 | C12: 136.35 | D12: 152.3 | E12: 142.13 | F12: 140.59 | G12: 141.96
A13: Total Liabilities | B13: 86.72 | C13: 129.49 | D13: 144.18 | E13: 132.56 | F13: 129.03 | G13: 129.96
A14: Total Debt | B14: 82.26 | C14: 123.76 | D14: 132.85 | E14: 124.02 | F14: 121.34 | G14: 120.17
A15: Total Equity | B15: 6.33 | C15: 6.86 | D15: 8.12 | E15: 9.57 | F15: 11.56 | G15: 11.99
A16: Cash And Cash Equivalents | B16: 8.98 | C16: 21.77 | D16: 15.43 | E16: 11.2 | F16: 8.99 | G16: 8.61
A17: Shares Outstanding (Mil) | B17: 421.18 | C17: 705.54 | D17: 705.56 | E17: 707.59 | F17: 709.74 | G17: 707.79
A18: Book Value Per Share | B18: 8.77 | C18: 9.49 | D18: 11.23 | E18: 13.24 | F18: 16.04 | G18: 16.64
A19: Total Debt To Equity | B19: 12.99 | C19: 18.04 | D19: 16.36 | E19: 12.96 | F19: 10.49 | G19: 10.02
A21: Income Statement (in Bil, except ratios) | B21: 44166 | C21: 44531 | D21: 44896 | E21: 45261 | F21: 45627 | G21: 03/31/2025
A22: Cash From Operating Activities | B22: -0.63 | C22: 1.26 | D22: 12.79 | E22: -3.42 | F22: -2.5 | G22: -2.5
A23: Cash From Investing Activities | B23: -0.22 | C23: -0.74 | D23: -0.02 | E23: -0.31 | F23: -0.22 | G23: -0.22
A24: Cash From Financing Activities | B24: 0.77 | C24: -0.06 | D24: -0.09 | E24: -0.18 | F24: 0.51 | G24: 0.51
A25: Free Cash Flow | B25: 0.81 | C25: 1.05 | D25: 1.53 | E25: 2.72 | F25: 2.66 | G25: 2.66
A26: Change in Cash | B26: -0.09 | C26: 0.46 | D26: 12.69 | E26: -3.91 | F26: -2.2 | G26: -2.2

Sheet BUZZI
A1: Income Statement (in Bil, except ratios) | B1: 43800 | C1: 44166 | D1: 44531 | E1: 44896 | F1: 45261 | G1: 45657
A2: Revenue | B2: 3.22 | C2: 3.22 | D2: 3.45 | E2: 4 | F2: 4.32 | G2: 4.31
A3: Revenue Growth % | B3: 0.1211 | C3: 0.0003 | D3: 0.0692 | E3: 0.1596 | F3: 0.0806 | G3: -0.001
A4: Gross Profit | B4: 2.03 | C4: 2.05 | D4: 2.09 | E4: 2.36 | F4: 2.75 | G4: 2.82
A5: Gross Profit Margin % | B5: 0.6305 | C5: 0.6364 | D5: 0.6069 | E5: 0.5917 | F5: 0.637 | G5: 0.6541
A6: Operating Income | B6: 0.47 | C6: 0.52 | D6: 0.53 | E6: 0.61 | F6: 0.98 | G6: 0.99
A7: Operating Margin % | B7: 0.1445 | C7: 0.1602 | D7: 0.155 | E7: 0.1531 | F7: 0.2259 | G7: 0.2296
A8: EBIT | B8: 0.52 | C8: 0.73 | D8: 0.66 | E8: 0.59 | F8: 1.13 | G8: 1.05
A9: EBIT Margin % | B9: 0.161 | C9: 0.2278 | D9: 0.1921 | E9: 0.1471 | F9: 0.2627 | G9: 0.2435
A10: EBITDA | B10: 0.78 | C10: 0.99 | D10: 0.91 | E10: 0.98 | F10: 1.38 | G10: 1.32
A11: EBITDA Margin % | B11: 0.2417 | C11: 0.3064 | D11: 0.2644 | E11: 0.2445 | F11: 0.3202 | G11: 0.3067
A12: Net Income | B12: 0.39 | C12: 0.56 | D12: 0.54 | E12: 0.46 | F12: 0.97 | G12: 0.94
... A36: Change in Cash | B36: 0.39 | C36: 0.45 | D36: -0.07 | E36: 0.1 | F36: -0.19 | G36: 0.28

Sheet NVDA
A1: Income Statement (in Bil, except ratios) | B1: 44197 | C1: 44562 | D1: 44927 | E1: 45292 | F1: 45658 | G1: 04/30/2025
A2: Revenue | B2: 16.68 | C2: 26.91 | D2: 26.97 | E2: 60.92 | F2: 130.5 | G2: 148.52
A3: Revenue Growth % | B3: 0.5273 | C3: 0.614 | D3: 0.0022 | E3: 1.2585 | F3: 1.142 | G3: 0.8617
A4: Gross Profit | B4: 10.4 | C4: 17.48 | D4: 15.36 | E4: 44.3 | F4: 97.86 | G4: 104.12
A5: Gross Profit Margin % | B5: 0.6234 | C5: 0.6493 | D5: 0.5693 | E5: 0.7272 | F5: 0.7499 | G5: 0.7011
A6: Operating Income | B6: 4.53 | C6: 10.04 | D6: 5.58 | E6: 32.97 | F6: 81.45 | G6: 86.18
A7: Operating Margin % | B7: 0.2718 | C7: 0.3731 | D7: 0.2068 | E7: 0.5412 | F7: 0.6242 | G7: 0.5803
A8: EBIT | B8: 4.54 | C8: 10.15 | D8: 4.18 | E8: 33.21 | F8: 82.49 | G8: 86.96
A9: EBIT Margin % | B9: 0.272 | C9: 0.3771 | D9: 0.1548 | E9: 0.5451 | F9: 0.6321 | G9: 0.5855
A10: EBITDA | B10: 5.63 | C10: 11.32 | D10: 5.72 | E10: 34.72 | F10: 84.38 | G10: 89.03
A11: EBITDA Margin % | B11: 0.3379 | C11: 0.4207 | D11: 0.212 | E11: 0.5699 | F11: 0.6466 | G11: 0.5994
A12: Net Income | B12: 4.33 | C12: 9.75 | D12: 4.37 | E12: 29.76 | F12: 72.88 | G12: 76.77
A13: Net Profit Margin % | B13: 0.2598 | C13: 0.3623 | D13: 0.1619 | E13: 0.4885 | F13: 0.5585 | G13: 0.5169
... A17: Total Dividends per Share | B17: 0.02 | C17: 0.02 | D17: 0.02 | E17: 0.02 | F17: 0.03 | G17: 0.04
A19: Balance Sheet (in Bil, except ratios) | B19: 44197 | C19: 44562 | D19: 44927 | E19: 45292 | F19: 45658 | G19: 04/30/2025
A20: Total Assets | B20: 28.79 | C20: 44.19 | D20: 41.18 | E20: 65.73 | F20: 111.6 | G20: 125.25
A21: Total Liabilities | B21: 11.9 | C21: 17.58 | D21: 19.08 | E21: 22.75 | F21: 32.27 | G21: 41.41
A22: Total Debt | B22: 7.72 | C22: 11.69 | D22: 12.03 | E22: 11.06 | F22: 10.27 | G22: 10.29
A23: Total Equity | B23: 16.89 | C23: 26.61 | D23: 22.1 | E23: 42.98 | F23: 79.33 | G23: 83.84
A24: Cash And Cash Equivalents | B24: 0.85 | C24: 1.99 | D24: 3.39 | E24: 7.28 | F24: 8.59 | G24: 15.23
A25: Working Capital | B25: 12.13 | C25: 24.49 | D25: 16.51 | E25: 33.71 | F25: 62.08 | G25: 63.39
A26: Shares Outstanding (Bil) | B26: 25 | C26: 24.6 | D26: 24.7 | E26: 24.49 | F26: 24.39 | G26: 24.39
A27: Book Value Per Share | B27: 0.68 | C27: 1.06 | D27: 0.9 | E27: 1.74 | F27: 3.24 | G27: 3.44
A28: Total Debt To Equity | B28: 0.46 | C28: 0.44 | D28: 0.54 | E28: 0.26 | F28: 0.13 | G28: 0.12
A30: Cash Flow Statement (in Bil, except ratios) | B30: 44197 | C30: 44562 | D30: 44927 | E30: 45292 | F30: 45658 | G30: 04/30/2025
A31: Cash From Operating Activities | B31: 5.82 | C31: 9.11 | D31: 5.64 | E31: 28.09 | F31: 64.09 | G31: 76.16
A32: Cash From Investing Activities | B32: -19.68 | C32: -9.83 | D32: 7.38 | E32: -10.57 | F32: -20.42 | G32: -19.94
A33: Cash From Financing Activities | B33: 3.8 | C33: 1.87 | D33: -11.62 | E33: -13.63 | F33: -42.36 | G33: -48.57
A34: Capital Expenditures | B34: 1.13 | C34: 0.98 | D34: 1.83 | E34: 1.07 | F34: 3.24 | G34: 4.09
A35: Free Cash Flow | B35: 5.4 | C35: 11.5 | D35: 6.01 | E35: 30.74 | F35: 70.24 | G35: 73.63
A36: Change in Cash | B36: -10.05 | C36: 1.14 | D36: 1.4 | E36: 3.89 | F36: 1.31 | G36: 7.65
